[{"pos":"adjective","pronUS":"https://www.oxfordlearnersdictionaries.com/media/english/us_pron/a/act/actua/actual__us_1_rr.mp3","phonsUS":"/ˈæktʃuəl/","level":"B2","meanings":[{"def":"used to emphasize something that is real or exists in fact","examples":["James looks younger than his wife but in actual fact (= really) he is five years older.","The actual cost was higher than we expected.","The actual number of unemployed is more than 15 million.","What were his actual words?","A variety of factors could cause our actual results to differ from the expected results.","The story of the film is based on actual events and people.","I need the actual figures, not an estimate.","How long have you been in your present job?","The factory cannot continue its current level of production."],"opposite":"","synonyms":""},{"def":"used to emphasize the most important part of something","examples":["The rehearsal was fabulous, the actual performance even better.","The wedding preparations take weeks but the actual ceremony takes less than an hour."],"opposite":"","synonyms":""}],"idioms":[],"phrasal":[],"related":["actual bodily harm","in (actual) fact"]}]