[{"pos":"adjective","pronUS":"https://www.oxfordlearnersdictionaries.com/media/english/us_pron/a/ama/amazi/amazing__us_2.mp3","phonsUS":"/əˈmeɪzɪŋ/","level":"A1","meanings":[{"def":"very surprising, especially in a way that you like or admire","examples":["an amazing feat/story/experience","That's amazing, isn't it?","The amazing thing is, he really believes he'll get away with it.","amazing to do something It was truly amazing to see how much work goes into a Broadway musical.","it is amazing how, what, etc… It's amazing how quickly people adapt.","it is amazing that… I find it amazing that people can be so irresponsible.","It’s amazing the difference a few polite words make.","I have some amazing news.","I made an amazing discovery today.","It's amazing how much better I feel.","The results of the treatment were nothing short of amazing.","It's amazing what you can do if you have to.","The market has an amazing variety of fish.","The service is amazing value for money.","The virus spread at amazing speed."],"opposite":"","synonyms":""},{"def":"very impressive; excellent","examples":["He makes the most amazing cakes.","I saw the most amazing film yesterday!","That looks pretty amazing, doesn't it?"],"opposite":"","synonyms":""}],"idioms":[],"phrasal":[],"related":["Amazing Grace"]}]