[{"pos":"noun","pronUS":"https://www.oxfordlearnersdictionaries.com/media/english/us_pron/c/cas/cash_/cash__us_1.mp3","phonsUS":"/kæʃ/","level":"A2","meanings":[{"def":"money in the form of coins or notes","examples":["How much cash do you have on you?","Customers are offered a 10% discount if they pay cash.","a cash payment","in cash Payments can be made by card or in cash.","The thieves stole £500 in cash.","I counted the money carefully.","Where can I change my money into dollars?","paper money (= money that is made of paper, not coins)","How much cash do you have on you?","Payments can be made by cheque or in cash.","The ticket machine doesn’t give change.","I don’t have any small change (= coins of low value).","I paid the bill in cash.","The bank should hold enough cash to satisfy customer demand.","We'll have to pay cash for the tickets.","You can pay by cheque or in cash."],"opposite":"","synonyms":"money"},{"def":"money in any form","examples":["The museum needs to find ways of raising cash.","I'm short of cash right now.","I'm constantly strapped for cash (= without enough money).","Local schools have been starved of cash for a number of years.","The company is desperate for an injection of cash to ease its debts.","The company is strapped for cash.","She refused to part with her hard-earned cash.","a chance to make some quick cash","They had a football match to raise cash for the hospital.","Imagine having to pay some of my hard-earned cash on a parking fine!","I refuse to spend my hard-earned cash on presents!"],"opposite":"","synonyms":""},{"def":"with immediate payment of cash","examples":["to pay for something cash down"],"opposite":"","synonyms":""},{"def":"if you pay for goods and services cash in hand, you pay in cash, especially so that the person being paid can avoid paying tax on the amount","examples":["a cash-in-hand payment of £20"],"opposite":"","synonyms":""},{"def":"a system of paying for goods when they are delivered","examples":[],"opposite":"","synonyms":""}],"idioms":[{"idiom":"cash down","def":"with immediate payment of cash","examples":["to pay for something cash down"]},{"idiom":"cash in hand","def":"if you pay for goods and services cash in hand, you pay in cash, especially so that the person being paid can avoid paying tax on the amount","examples":["a cash-in-hand payment of £20"]},{"idiom":"cash on delivery","def":"a system of paying for goods when they are delivered","examples":[]}],"phrasal":[],"related":["e-cash","cash bar","cash box","cash cow","cash in","cash up","cash card","cash crop","cash desk","cash flow","cash-rich","cold cash","hard cash","petty cash","Cash","cash machine","cash register","cash-starved","cash-strapped"]},{"pos":"verb","level":"","meanings":[{"def":"to exchange a cheque for the amount of money that it is worth","examples":["At that time, traveller's cheques could be cashed at most hotels.","The company cashed my cheque but then failed to send the goods I’d ordered."],"opposite":"","synonyms":""},{"def":"to die","examples":["He cashed in his chips last summer aged 65."],"opposite":"","synonyms":""}],"idioms":[{"idiom":"cash in your chips","def":"to die","examples":["He cashed in his chips last summer aged 65."]}],"phrasal":["cash in","cash up"],"related":[]}]