[{"pos":"adjective","pronUS":"https://www.oxfordlearnersdictionaries.com/media/english/us_pron/d/dea/dear_/dear__us_1.mp3","phonsUS":"/dɪr/","level":"A1","meanings":[{"def":"used at the beginning of a letter before the name or title of the person that you are writing to","examples":["Dear Sir or Madam","Dear Mrs Jones","Dear Beth/Dad/Aunt Susan","(old-fashioned) My dear sister"],"opposite":"","synonyms":""},{"def":"loved by or important to somebody","examples":["He's one of my dearest friends.","They are grieving over their dear departed ones.","dear to somebody Her daughter is very dear to her.","They lost everything that was dear to them.","Kate is a very dear friend of mine.","Congratulations, my dear!","The team is responsible for conserving red deer in the forest."],"opposite":"","synonyms":""},{"def":"used in speech or writing to address somebody in a polite or friendly way","examples":["Martin, my dear fellow…","Take my advice, dear reader."],"opposite":"","synonyms":""},{"def":"expensive; costing a lot of money","examples":["Everything's so dear now, isn't it?","There was a shortage of potatoes, and they became dear."],"opposite":"","synonyms":""},{"def":"having a lot of importance and interest for somebody","examples":[],"opposite":"","synonyms":""},{"def":"used to describe somebody in a way that shows love","examples":["Dear old Sue! I knew she'd help.","Their baby's a dear little thing.","It's always good to hear from dear old Harry!"],"opposite":"","synonyms":""},{"def":"as hard or as fast as possible","examples":["She was holding on to the rope for dear life.","Run for your life!"],"opposite":"","synonyms":""},{"def":"to hold somebody/something very tightly because you are afraid","examples":[],"opposite":"","synonyms":""},{"def":"to care very much for somebody/something; to value somebody/something highly","examples":["He had destroyed everything we held dear."],"opposite":"","synonyms":""},{"def":"your close family and friends","examples":[],"opposite":"","synonyms":""}],"idioms":[{"idiom":"close/dear/near to somebody’s heart","def":"having a lot of importance and interest for somebody","examples":[]},{"idiom":"dear old/little…","def":"used to describe somebody in a way that shows love","examples":["Dear old Sue! I knew she'd help.","Their baby's a dear little thing.","It's always good to hear from dear old Harry!"]},{"idiom":"for dear life | for your life","def":"as hard or as fast as possible","examples":["She was holding on to the rope for dear life.","Run for your life!"]},{"idiom":"hang/hold on for dear life","def":"to hold somebody/something very tightly because you are afraid","examples":[]},{"idiom":"hold somebody/something dear","def":"to care very much for somebody/something; to value somebody/something highly","examples":["He had destroyed everything we held dear."]},{"idiom":"your nearest and dearest","def":"your close family and friends","examples":[]}],"phrasal":[],"related":["old dear","Dear Abby","Dear John letter","Dear John","dear wife","Dear Sir/Sirs","Dear John letters","hang/hold on for dear life","hold/hang on for dear life","oh (dear) God","cost somebody dear","close/dear/near to somebody’s heart"]},{"pos":"exclamation","level":"A2","meanings":[{"def":"used in expressions that show that you are surprised, upset, annoyed or worried","examples":["Oh dear! I think I've lost my purse!","Oh dear! What a shame.","Dear me! What a mess!","Dear oh dear! What are you going to do now?"],"opposite":"","synonyms":""}],"idioms":[],"phrasal":[],"related":[]},{"pos":"noun","level":"","meanings":[{"def":"a kind person","examples":["Isn't he a dear?","Be a dear and fetch me my coat."],"opposite":"","synonyms":""},{"def":"used when speaking to somebody you love","examples":["Would you like a drink, dear?","Come here, my dear.","Kate is a very dear friend of mine.","Congratulations, my dear!","The team is responsible for conserving red deer in the forest."],"opposite":"","synonyms":""},{"def":"used when speaking to somebody in a friendly way, for example by an older person to a young person or a child","examples":["What's your name, dear?"],"opposite":"","synonyms":""}],"idioms":[],"phrasal":[],"related":[]},{"pos":"adverb","level":"","meanings":[{"def":"at a high price","examples":["to buy cheap and sell dear"],"opposite":"","synonyms":""},{"def":"to cost somebody a lot of money","examples":["The campaign for the presidency has cost him dear."],"opposite":"","synonyms":""},{"def":"to make somebody suffer a lot","examples":["That one mistake has cost him dear over the years."],"opposite":"","synonyms":""}],"idioms":[{"idiom":"cost somebody dear","def":"to cost somebody a lot of money","examples":["The campaign for the presidency has cost him dear.","That one mistake has cost him dear over the years."]}],"phrasal":[],"related":[]}]