[{"pos":"adjective","pronUS":"https://www.oxfordlearnersdictionaries.com/media/english/us_pron/l/loc/local/local__us_2.mp3","phonsUS":"/ˈləʊkl/","level":"A1","meanings":[{"def":"belonging to or connected with the particular place or area that you are talking about or with the place where you live","examples":["local people/residents/businesses","members of the local community","the local police","local elections","A local man was accused of the murder.","Our children go to the local school.","a local newspaper (= one that gives local news)","decisions made at the local level","It was difficult to understand the local dialect."],"opposite":"","synonyms":""},{"def":"affecting only one part of the body","examples":["Her tooth was extracted under local anaesthetic."],"opposite":"","synonyms":""}],"idioms":[],"phrasal":[],"related":["lo-cal","local bus","local call","local radio","local time","local colour","Thomson Local","local authority","local government","local area network","Local Education Authority","Ministry of Housing, Communities and Local Government","local buses","local color","local authorities","local governments","local area networks","Independent Local Radio"]},{"pos":"noun","level":"B1","meanings":[{"def":"a person who lives in a particular place or district","examples":["The locals are very friendly.","She’s beginning to sound like one of the locals.","The victim was a local who jogged regularly in the park.","Tensions have been growing between students and locals in the area.","The troops arranged a friendly football match with locals.","We chatted with the locals at the island's only post office."],"opposite":"","synonyms":""},{"def":"a pub near where you live","examples":["I called in at my local on the way home.","It's a friendly local with good beer."],"opposite":"","synonyms":""},{"def":"a branch of a labor union","examples":[],"opposite":"","synonyms":""},{"def":"a bus or train that stops at all places on the route","examples":[],"opposite":"","synonyms":""}],"idioms":[],"phrasal":[],"related":[]}]