[{"pos":"noun","pronUS":"https://www.oxfordlearnersdictionaries.com/media/english/us_pron/s/sig/sight/sight__us_1.mp3","phonsUS":"/saɪt/","level":"B1","meanings":[{"def":"the ability to see","examples":["to lose your sight (= to become blind)","She has very good sight.","The disease has affected her sight.","He has very little sight in his right eye.","It's important that you have regular sight tests.","He's lost the sight of one eye.","His sight returned by degrees.","I think my sight is beginning to go.","The surgeons battled to save her sight.","This disease is the main cause of sight loss among those aged 50 and over."],"opposite":"","synonyms":""},{"def":"the act of seeing somebody/something","examples":["sight of somebody/something She kept sight of him in her mirror.","She caught sight of a car in the distance.","After ten days at sea, we had our first sight of land.","The mere sight of him makes me want to scream.","sight of somebody/something doing something The sight of him hobbling off so early in the match depressed everyone.","at the sight He laughed quietly to himself at the sight.","at the sight of somebody/something I have been known to faint at the sight of blood.","on sight The soldiers were given orders to shoot on sight (= as soon as they saw somebody).","Her knees went weak at the sight of him.","Thankfully, we were spared the sight of his naked body.","The mere sight of her sitting there made his heart beat faster.","I witnessed the awful sight of children drinking dirty water from puddles.","We will soon get our first sight of the Statue of Liberty.","I know her by sight (= recognize but do not know her)."],"opposite":"","synonyms":""},{"def":"the area or distance within which somebody can see or something can be seen","examples":["in sight There was no one in sight.","They stole everything in sight.","The end is in sight (= will happen soon).","The goats ate everything in sight.","in sight of somebody/something At last we came in sight of a few houses.","A bicycle came into sight on the main road.","within sight They marched on and by the following afternoon the enemy was within sight.","within sight of somebody/something He sprinted ahead as they came within sight of the finishing line.","out of sight Leave any valuables in your car out of sight.","Keep out of sight (= stay where you cannot be seen).","out of somebody's sight She never lets her daughter out of her sight (= always keeps her where she can see her).","Get out of my sight! (= Go away!)","The boat disappeared from sight.","The house was hidden from sight behind some trees.","He looked up the street, but there was no one in sight.","Leave any valuables in your car out of sight.","The lake soon came into view.","The couple moved outside her field of vision (= total area you can see from a particular position).","He won't let the children leave his sight.","Her father was nowhere in sight.","The cricket ground was situated within sight of both village pubs.","They waited until the enemy was in plain sight.","He strode by, in full sight of the guards.","He didn't shoot until he had a clear sight of the goal."],"opposite":"","synonyms":"sight"},{"def":"a thing that you see or can see","examples":["Roadside stalls are a common sight in the city.","It's a spectacular sight as the flamingos lift into the air.","The museum attempts to recreate the sights and sounds of wartime Britain.","He was a sorry sight, soaked to the skin and shivering.","The bird is now a rare sight in this country.","He became a familiar sight on the streets of Oxford.","The gardens were a beautiful sight to behold in the twilight.","She would never forget the sight of Machu Picchu appearing out of the mist.","Follow this link to reach the official site.","The French government had plans to site a third major airport for Paris at Chaulnes.","The cottage had a delightful sea view.","It’s a spectacular sight as the flamingos lift into the air.","It was a delightful rural scene.","The tower offers a breathtaking panorama of Prague.","An appalling sight greeted her.","Dan's face was a welcome sight.","I'm not a pretty sight when I get out of bed in the morning.","The military parade was quite a sight.","This is a sight not often seen on concert stages in this country."],"opposite":"","synonyms":"view"},{"def":"the interesting places, especially in a town or city, that are often visited by tourists","examples":["We're going to Paris for the weekend to see the sights.","The next day I did the sights of the city.","It's best if you can get someone local to show you the sights."],"opposite":"","synonyms":""},{"def":"a person or thing that looks silly, untidy, unpleasant, etc.","examples":["She looks a sight in that hat!"],"opposite":"","synonyms":""},{"def":"a device that you look through to aim a gun, etc. or to look at something through a telescope, etc.","examples":["He had the deer in his sights now.","to align the sights on the target","(figurative) Even as a young actress, she always had Hollywood firmly in her sights (= as her final goal).","Rossi has the defending champion in her sights in tomorrow's race.","She turned her sights on (= decided to examine) Florida's adoption laws."],"opposite":"","synonyms":""},{"def":"when you first begin to consider something","examples":["At first sight, it may look like a generous offer, but always read the small print."],"opposite":"","synonyms":""},{"def":"when you see somebody/something for the first time","examples":["It was love at first sight (= we fell in love the first time we saw each other).","We fell in love with the house at first sight.","He looked at first sight like a tourist."],"opposite":"","synonyms":""},{"def":"to hate, etc. somebody/something very much","examples":["I can't stand the sight of him!","We've shared an office for too long and we're sick of the sight of each other."],"opposite":"","synonyms":""},{"def":"to appear, especially when moving gradually closer from a long way off","examples":["A ship hove into sight.","Like a galleon in full sail, Cara hove into view."],"opposite":"","synonyms":""},{"def":"in somebody’s opinion","examples":["We are all equal in the sight of God."],"opposite":"","synonyms":""},{"def":"to recognize somebody without knowing them well","examples":[],"opposite":"","synonyms":""},{"def":"to become no longer able to see somebody/something","examples":["They finally lost sight of land."],"opposite":"","synonyms":""},{"def":"to stop considering something; to forget something","examples":["We must not lose sight of our original aim."],"opposite":"","synonyms":""},{"def":"not pleasant to look at","examples":["You should have seen him in his swimming trunks—not a pretty sight!"],"opposite":"","synonyms":""},{"def":"impossible for anyone to find or see","examples":["I wanted to talk to him but he was nowhere to be found.","The children were nowhere to be seen.","A peace settlement is nowhere in sight (= is not likely in the near future)."],"opposite":"","synonyms":""},{"def":"used to say somebody will quickly be forgotten when they are no longer with you","examples":[],"opposite":"","synonyms":""},{"def":"to expect more/less from a situation","examples":["If they can’t afford such a big house, they’ll just have to lower their sights a little.","After failing to get into university, he lowered his sights and got a job in a shop."],"opposite":"","synonyms":""},{"def":"to decide that you want something and to try very hard to get it","examples":["She's set her sights on getting into Harvard.","I had set my sights on a career in journalism.","He says he wants to win the trophy, but I think he's setting his sights too high.","She has her sights set on becoming a writer."],"opposite":"","synonyms":""},{"def":"very much better; much too good, etc.","examples":["She's done a darn sight better than I have.","It's worth a damn sight more than I thought."],"opposite":"","synonyms":""},{"def":"a person or thing that you are pleased to see; something that is very pleasant to look at","examples":[],"opposite":"","synonyms":""},{"def":"if you buy something sight unseen, you do not have an opportunity to see it before you buy it","examples":["I bought it, sight unseen."],"opposite":"","synonyms":""}],"idioms":[{"idiom":"at first sight","def":"when you first begin to consider something","examples":["At first sight, it may look like a generous offer, but always read the small print.","It was love at first sight (= we fell in love the first time we saw each other).","We fell in love with the house at first sight.","He looked at first sight like a tourist."]},{"idiom":"hate, be sick of, etc. the sight of somebody/something","def":"to hate, etc. somebody/something very much","examples":["I can't stand the sight of him!","We've shared an office for too long and we're sick of the sight of each other."]},{"idiom":"heave into sight/view","def":"to appear, especially when moving gradually closer from a long way off","examples":["A ship hove into sight.","Like a galleon in full sail, Cara hove into view."]},{"idiom":"in the sight of somebody/in somebody’s sight","def":"in somebody’s opinion","examples":["We are all equal in the sight of God."]},{"idiom":"know somebody by sight","def":"to recognize somebody without knowing them well","examples":[]},{"idiom":"lose sight of somebody/something","def":"to become no longer able to see somebody/something","examples":["They finally lost sight of land.","We must not lose sight of our original aim."]},{"idiom":"not a pretty sight","def":"not pleasant to look at","examples":["You should have seen him in his swimming trunks—not a pretty sight!"]},{"idiom":"nowhere to be found/seen | nowhere in sight","def":"impossible for anyone to find or see","examples":["I wanted to talk to him but he was nowhere to be found.","The children were nowhere to be seen.","A peace settlement is nowhere in sight (= is not likely in the near future)."]},{"idiom":"out of sight, out of mind","def":"used to say somebody will quickly be forgotten when they are no longer with you","examples":[]},{"idiom":"raise/lower your sights","def":"to expect more/less from a situation","examples":["If they can’t afford such a big house, they’ll just have to lower their sights a little.","After failing to get into university, he lowered his sights and got a job in a shop."]},{"idiom":"set your sights on something/on doing something","def":"to decide that you want something and to try very hard to get it","examples":["She's set her sights on getting into Harvard.","I had set my sights on a career in journalism.","He says he wants to win the trophy, but I think he's setting his sights too high.","She has her sights set on becoming a writer."]},{"idiom":"a (damn, etc.) sight better, etc. | a (damn, etc.) sight too good, etc.","def":"very much better; much too good, etc.","examples":["She's done a darn sight better than I have.","It's worth a damn sight more than I thought."]},{"idiom":"a sight for sore eyes","def":"a person or thing that you are pleased to see; something that is very pleasant to look at","examples":[]},{"idiom":"sight unseen","def":"if you buy something sight unseen, you do not have an opportunity to see it before you buy it","examples":["I bought it, sight unseen."]}],"phrasal":[],"related":["short sight","sight-line","sight-read","second sight","sight-reader","sight-reading","line of sight","long sight","sight-reads","sight-readed","sight-readers","lines of sight","nowhere in sight","not a pretty sight","heave into sight/view"]},{"pos":"verb","level":"","meanings":[{"def":"to suddenly see something, especially something you have been looking for","examples":["After twelve days at sea, they sighted land."],"opposite":"","synonyms":""}],"idioms":[],"phrasal":[],"related":[]}]